ImgTiler/ImageTiler.py
ImgTiler/__init__.py
image_tiller-0.1.2.1.dist-info/LICENSE
image_tiller-0.1.2.1.dist-info/METADATA
image_tiller-0.1.2.1.dist-info/WHEEL
image_tiller-0.1.2.1.dist-info/top_level.txt
image_tiller-0.1.2.1.dist-info/RECORD
