Metadata-Version: 2.1
Name: image-tiller
Version: 0.1.2.1
Summary: ('image_tiller is a Python library for tiling and retiling images. It can be used for splitting large images into smaller tiles for other applications like Training Deep Learning models, inference on large images, etc.',)
Home-page: https://github.com/CollinsWakholi/ImgTiler
Download-URL: https://github.com/collinswakholi/ImgTiler/archive/refs/tags/v0.1.0.tar.gz
Author: Collins Wakholi
Author-email: wcoln@yahoo.com
Classifier: License :: OSI Approved :: MIT License
Classifier: Programming Language :: Python :: 3.11
Classifier: Operating System :: OS Independent
License-File: LICENSE
Requires-Dist: numpy
Requires-Dist: matplotlib
Requires-Dist: opencv-python
